wallpy/__init__.py
wallpy/__main__.py
wallpy/cli/__init__.py
wallpy/cli/app.py
wallpy/cli/config.py
wallpy/cli/logs.py
wallpy/cli/pack.py
wallpy/cli/service.py
wallpy/cli/utils.py
wallpy/config.py
wallpy/data/config.toml
wallpy/data/packs/default/images/ascii_adam_black.jpg
wallpy/data/packs/default/images/ascii_adam_white.jpg
wallpy/data/packs/default/schedule.toml
wallpy/data/packs/zelda-wind-walker/images/dawn1.jpg
wallpy/data/packs/zelda-wind-walker/images/dawn2.jpg
wallpy/data/packs/zelda-wind-walker/images/dawn3.jpg
wallpy/data/packs/zelda-wind-walker/images/dusk1.jpg
wallpy/data/packs/zelda-wind-walker/images/dusk2.jpg
wallpy/data/packs/zelda-wind-walker/images/dusk3.jpg
wallpy/data/packs/zelda-wind-walker/images/morning1.jpg
wallpy/data/packs/zelda-wind-walker/images/morning2.jpg
wallpy/data/packs/zelda-wind-walker/images/morning3.jpg
wallpy/data/packs/zelda-wind-walker/images/morning4.jpg
wallpy/data/packs/zelda-wind-walker/images/night1.jpg
wallpy/data/packs/zelda-wind-walker/images/night2.jpg
wallpy/data/packs/zelda-wind-walker/images/night3.jpg
wallpy/data/packs/zelda-wind-walker/images/night4.jpg
wallpy/data/packs/zelda-wind-walker/images/night5.jpg
wallpy/data/packs/zelda-wind-walker/images/night6.jpg
wallpy/data/packs/zelda-wind-walker/schedule.toml
wallpy/elevate.py
wallpy/engine.py
wallpy/models.py
wallpy/schedule.py
wallpy/scripts/windows/install_task.ps1
wallpy/service.py
wallpy/validate.py
wallpy-2.25.0.dist-info/entry_points.txt
wallpy-2.25.0.dist-info/LICENSE
wallpy-2.25.0.dist-info/METADATA
wallpy-2.25.0.dist-info/WHEEL
wallpy-2.25.0.dist-info/RECORD
