Metadata-Version: 2.3
Name: wallpy
Version: 2.25.0
Summary: Dynamic wallpaper engine to change wallpaper based on time of day and location
Author: Jaiyank Saxena
Author-email: siphyshu@gmail.com
Requires-Python: >=3.9,<4.0
Classifier: Programming Language :: Python :: 3
Classifier: Programming Language :: Python :: 3.9
Classifier: Programming Language :: Python :: 3.10
Classifier: Programming Language :: Python :: 3.11
Classifier: Programming Language :: Python :: 3.12
Classifier: Programming Language :: Python :: 3.13
Requires-Dist: APScheduler (>=3.10.4,<4.0.0)
Requires-Dist: Pillow (>=10.2.0,<11.0.0)
Requires-Dist: astral (>=3.2,<4.0)
Requires-Dist: platformdirs (>=3.2.0,<4.0.0)
Requires-Dist: psutil (>=5.9.4,<6.0.0)
Requires-Dist: pydantic (>=2.10.6,<3.0.0)
Requires-Dist: pywin32 (>=308,<309) ; sys_platform == "win32"
Requires-Dist: rich (>=13.9.4,<14.0.0)
Requires-Dist: tomli (>=2.0.1,<3.0.0)
Requires-Dist: tomli-w (>=1.0.0,<2.0.0)
Requires-Dist: typer (>=0.15.1,<0.16.0)
Requires-Dist: watchdog (>=6.0.0,<7.0.0)
